mongo_watcher/__init__.py
mongo_watcher/watcher.py
pycasbin_mongo_watcher-0.1.0.dist-info/licenses/LICENSE
pycasbin_mongo_watcher-0.1.0.dist-info/METADATA
pycasbin_mongo_watcher-0.1.0.dist-info/WHEEL
pycasbin_mongo_watcher-0.1.0.dist-info/top_level.txt
pycasbin_mongo_watcher-0.1.0.dist-info/RECORD
